[{"country": "Poland", "point": 389}, {"country": "Italy", "point": 369}, {"country": "France", "point": 368}, {"country": "Brazil", "point": 361}, {"country": "Russia", "point": 352}, {"country": "USA", "point": 333}, {"country": "Japan", "point": 277}, {"country": "Argentina", "point": 273}, {"country": "Slovenia", "point": 268}, {"country": "Iran", "point": 267}, {"country": "Serbia", "point": 253}, {"country": "Cuba", "point": 230}, {"country": "Netherlands", "point": 228}, {"country": "T\u00fcrkiye", "point": 200}, {"country": "Canada", "point": 189}, {"country": "Ukraine", "point": 187}, {"country": "Germany", "point": 184}, {"country": "Mexico", "point": 175}, {"country": "Tunisia", "point": 172}, {"country": "Egypt", "point": 157}, {"country": "Belgium", "point": 153}, {"country": "Czech Republic", "point": 152}, {"country": "Bulgaria", "point": 152}, {"country": "Finland", "point": 152}, {"country": "Qatar", "point": 152}, {"country": "China", "point": 151}, {"country": "Chile", "point": 144}, {"country": "Puerto Rico", "point": 139}, {"country": "Portugal", "point": 139}, {"country": "Cameroon", "point": 136}, {"country": "Romania", "point": 134}, {"country": "Croatia", "point": 130}, {"country": "Dominican Republic", "point": 129}, {"country": "Korea", "point": 129}, {"country": "Spain", "point": 127}, {"country": "Greece", "point": 127}, {"country": "Switzerland", "point": 125}, {"country": "Belarus", "point": 121}, {"country": "Australia", "point": 116}, {"country": "Slovak Republic", "point": 112}, {"country": "Montenegro", "point": 112}, {"country": "Estonia", "point": 106}, {"country": "North Macedonia", "point": 102}, {"country": "Denmark", "point": 99}, {"country": "Chinese Taipei", "point": 91}, {"country": "Latvia", "point": 89}, {"country": "Austria", "point": 86}, {"country": "Luxembourg", "point": 83}, {"country": "Azerbaijan", "point": 83}, {"country": "Hungary", "point": 79}, {"country": "Colombia", "point": 70}, {"country": "Bosnia and Herzegovina", "point": 68}, {"country": "Norway", "point": 68}, {"country": "Pakistan", "point": 66}, {"country": "Albania", "point": 66}, {"country": "Morocco", "point": 65}, {"country": "Venezuela", "point": 60}, {"country": "Cyprus", "point": 51}, {"country": "Sweden", "point": 48}, {"country": "Faroe Islands", "point": 45}, {"country": "Georgia", "point": 45}, {"country": "Israel", "point": 44}, {"country": "Peru", "point": 43}, {"country": "Thailand", "point": 42}, {"country": "Kazakhstan", "point": 39}, {"country": "Kenya", "point": 39}, {"country": "Guatemala", "point": 37}, {"country": "India", "point": 35}, {"country": "Algeria", "point": 34}, {"country": "Iceland", "point": 32}, {"country": "Uganda", "point": 30}, {"country": "Congo Democratic Republic", "point": 29}, {"country": "Suriname", "point": 28}, {"country": "Burundi", "point": 25}, {"country": "Rwanda", "point": 24}, {"country": "Bahrain", "point": 24}, {"country": "Trinidad & Tobago", "point": 23}]