[{"country": "Poland", "point": 408.96}, {"country": "United States", "point": 375.29}, {"country": "Italy", "point": 365.85}, {"country": "Brazil", "point": 337.28}, {"country": "Japan", "point": 334.34}, {"country": "Argentina", "point": 318.81}, {"country": "France", "point": 314.43}, {"country": "Slovenia", "point": 297.22}, {"country": "Serbia", "point": 265.42}, {"country": "Netherlands", "point": 244.87}, {"country": "Iran", "point": 243.55}, {"country": "Cuba", "point": 200.49}, {"country": "T\u00fcrkiye", "point": 195.47}, {"country": "Germany", "point": 191.59}, {"country": "Ukraine", "point": 188.62}, {"country": "Canada", "point": 186.38}, {"country": "Qatar", "point": 181.45}, {"country": "Mexico", "point": 176.82}, {"country": "Tunisia", "point": 173.32}, {"country": "Egypt", "point": 160.01}, {"country": "Czechia", "point": 158.3}, {"country": "Portugal", "point": 154.43}, {"country": "Belgium", "point": 147.55}, {"country": "Romania", "point": 143.69}, {"country": "Cameroon", "point": 142.31}, {"country": "Croatia", "point": 142.14}, {"country": "Chile", "point": 137.68}, {"country": "Korea", "point": 137.46}, {"country": "Finland", "point": 135.67}, {"country": "China", "point": 134.52}, {"country": "Bulgaria", "point": 134.0}, {"country": "Puerto Rico", "point": 128.92}, {"country": "Spain", "point": 124.11}, {"country": "Dominican Republic", "point": 120.47}, {"country": "Australia", "point": 118.27}, {"country": "Greece", "point": 113.37}, {"country": "North Macedonia", "point": 112.36}, {"country": "Switzerland", "point": 110.3}, {"country": "Slovakia", "point": 107.82}, {"country": "Latvia", "point": 105.46}, {"country": "Estonia", "point": 100.62}, {"country": "Montenegro", "point": 98.92}, {"country": "Chinese Taipei", "point": 92.34}, {"country": "Luxembourg", "point": 83.5}, {"country": "Azerbaijan", "point": 83.33}, {"country": "Colombia", "point": 82.68}, {"country": "Denmark", "point": 82.44}, {"country": "Hungary", "point": 82.2}, {"country": "Austria", "point": 81.05}, {"country": "Morocco", "point": 79.6}, {"country": "Pakistan", "point": 74.27}, {"country": "Libya", "point": 70.35}, {"country": "Bosnia and Herzegovina", "point": 68.35}, {"country": "Norway", "point": 68.29}, {"country": "Albania", "point": 66.15}, {"country": "Indonesia", "point": 61.27}, {"country": "Venezuela", "point": 60.5}, {"country": "Kazakhstan", "point": 57.91}, {"country": "Vietnam", "point": 57.9}, {"country": "Cyprus", "point": 52.8}, {"country": "Israel ", "point": 51.43}, {"country": "Philippines", "point": 50.71}, {"country": "Saudi Arabia", "point": 49.3}, {"country": "Sweden", "point": 48.36}, {"country": "Sri Lanka", "point": 48.01}, {"country": "Afghanistan", "point": 47.06}, {"country": "Macao, China", "point": 45.08}, {"country": "Thailand", "point": 44.49}, {"country": "Bangladesh", "point": 43.02}, {"country": "Algeria", "point": 41.83}, {"country": "India", "point": 40.23}, {"country": "Bahrain", "point": 39.98}, {"country": "Faroe Islands", "point": 37.0}, {"country": "Georgia", "point": 36.86}, {"country": "Peru", "point": 36.03}, {"country": "Mali", "point": 35.93}, {"country": "Chad", "point": 34.94}, {"country": "Guatemala", "point": 33.66}, {"country": "Ghana", "point": 33.14}, {"country": "Iceland", "point": 32.01}, {"country": "Iraq", "point": 31.53}, {"country": "Uganda", "point": 29.72}, {"country": "Kenya", "point": 29.1}, {"country": "Congo", "point": 29.06}, {"country": "Suriname", "point": 27.99}, {"country": "Uzbekistan", "point": 27.71}, {"country": "Rwanda", "point": 25.51}, {"country": "Trinidad and Tobago", "point": 22.51}, {"country": "Hong Kong, China", "point": 18.57}, {"country": "Mongolia", "point": 15.01}, {"country": "Burundi", "point": 14.06}, {"country": "Tanzania", "point": 10.28}]