[{"country": "Brazil", "point": 378.24}, {"country": "United States", "point": 368.0}, {"country": "Serbia", "point": 358.35}, {"country": "Italy", "point": 357.87}, {"country": "China", "point": 350.97}, {"country": "T\u00fcrkiye", "point": 327.13}, {"country": "Japan", "point": 325.39}, {"country": "Poland", "point": 291.25}, {"country": "Russia", "point": 277.59}, {"country": "Dominican Republic", "point": 260.93}, {"country": "Belgium", "point": 241.55}, {"country": "Germany", "point": 228.61}, {"country": "Netherlands", "point": 225.59}, {"country": "Thailand", "point": 210.55}, {"country": "Canada", "point": 204.95}, {"country": "Bulgaria", "point": 194.29}, {"country": "Puerto Rico", "point": 176.35}, {"country": "Colombia", "point": 162.61}, {"country": "Czechia", "point": 162.43}, {"country": "Mexico", "point": 160.05}, {"country": "France", "point": 159.08}, {"country": "Ukraine", "point": 150.28}, {"country": "Argentina", "point": 149.34}, {"country": "Slovenia", "point": 139.59}, {"country": "Korea", "point": 138.1}, {"country": "Peru", "point": 135.79}, {"country": "Cuba", "point": 131.59}, {"country": "Slovakia", "point": 128.78}, {"country": "Kenya", "point": 127.45}, {"country": "Croatia", "point": 124.24}, {"country": "Cameroon", "point": 122.19}, {"country": "Sweden", "point": 121.08}, {"country": "Greece", "point": 119.15}, {"country": "Bosnia and Herzegovina", "point": 118.34}, {"country": "Spain", "point": 116.13}, {"country": "Belarus", "point": 116.06}, {"country": "Romania", "point": 112.59}, {"country": "Hungary", "point": 105.43}, {"country": "Azerbaijan", "point": 103.38}, {"country": "Finland", "point": 100.67}, {"country": "Austria", "point": 100.24}, {"country": "Israel", "point": 91.24}, {"country": "Portugal", "point": 90.18}, {"country": "Montenegro", "point": 89.09}, {"country": "Kazakhstan", "point": 86.03}, {"country": "Estonia", "point": 80.76}, {"country": "Switzerland", "point": 79.73}, {"country": "Costa Rica", "point": 76.35}, {"country": "Denmark", "point": 70.84}, {"country": "Norway", "point": 55.85}, {"country": "Nicaragua", "point": 53.56}, {"country": "Latvia", "point": 52.89}, {"country": "Morocco", "point": 50.86}, {"country": "North Macedonia", "point": 43.73}, {"country": "Faroe Islands", "point": 39.71}, {"country": "Georgia", "point": 39.32}, {"country": "Cyprus", "point": 35.41}, {"country": "Senegal", "point": 34.45}, {"country": "Iceland", "point": 33.24}, {"country": "Luxembourg", "point": 32.46}, {"country": "Tunisia", "point": 23.79}, {"country": "Venezuela", "point": 21.6}, {"country": "Venezuela", "point": 21.6}]